netmanagement/__init__.py
netmanagement/core.py
netmanagement-0.1.1.dist-info/licenses/LICENSE
requests/__init__.py
netmanagement-0.1.1.dist-info/METADATA
netmanagement-0.1.1.dist-info/WHEEL
netmanagement-0.1.1.dist-info/top_level.txt
netmanagement-0.1.1.dist-info/RECORD
